README.md
setup.py
tarcom/__init__.py
tarcom.egg-info/PKG-INFO
tarcom.egg-info/SOURCES.txt
tarcom.egg-info/dependency_links.txt
tarcom.egg-info/top_level.txt