Metadata-Version: 2.1
Name: tarcom
Version: 0.1.5
Summary: TarCo Communication (tarcom) - Communicate with network devices using TCP (Server and Client). Internal Use Only (Use at your own risk)
Home-page: https://tarcosolutions.com
Author: Tarek Moghrabi
Author-email: tarexmo@outlook.com
License: MIT
Platform: UNKNOWN
Classifier: Programming Language :: Python :: 3
Classifier: License :: OSI Approved :: MIT License
Classifier: Operating System :: OS Independent
